mdsphinx/__init__.py
mdsphinx/__main__.py
mdsphinx/config.py
mdsphinx/core/__init__.py
mdsphinx/core/environment.py
mdsphinx/core/generate.py
mdsphinx/core/prepare.py
mdsphinx/core/process.py
mdsphinx/core/quickstart.py
mdsphinx/logger.py
mdsphinx/select.py
mdsphinx/tempdir.py
mdsphinx/templates/conf.py.jinja
mdsphinx/templates/index.rst.jinja
mdsphinx/types.py
mdsphinx-1.11.0.dist-info/METADATA
mdsphinx-1.11.0.dist-info/WHEEL
mdsphinx-1.11.0.dist-info/entry_points.txt
mdsphinx-1.11.0.dist-info/RECORD
