Metadata-Version: 2.4
Name: mdsphinx
Version: 1.11.0
Summary: Convert markdown to any output that Sphinx supports
License: WTFPL
Author: Adam Gagorik
Author-email: adam.gagorik@gmail.com
Requires-Python: >=3.12,<4.0
Classifier: License :: Other/Proprietary License
Classifier: Programming Language :: Python :: 3
Classifier: Programming Language :: Python :: 3.12
Classifier: Programming Language :: Python :: 3.13
Classifier: Programming Language :: Python :: 3.14
Requires-Dist: jinja2 (>=3.1.4,<4.0.0)
Requires-Dist: jinja2-mermaid-extension (>=1.1.3,<2.0.0)
Requires-Dist: natsort (>=8.4.0,<9.0.0)
Requires-Dist: networkx (>=3.4.2,<4.0.0)
Requires-Dist: pyyaml (>=6.0.1,<7.0.0)
Requires-Dist: typer (>=0.12.3,<0.13.0)
Project-URL: Repository, https://github.com/AdamGagorik/mdsphinx
